[
  {
    "question": "Consider the semidefinite program over a symmetric 2x2 matrix X:\nMinimize <C, X> subject to <A_i, X> = b_i for i=1..1, and X is positive semidefinite (X \u2ab0 0).\n\nC = [[0, 0.5], [0.5, -3]]\nA_1 = [[1, -0.5], [-0.5, -1]]\nb_1 = 5.0\n\nWhat is the minimum value of <C, X> (rounded to 3 decimals)?",
    "answer": "-17.232125304623302"
  },
  {
    "question": "Consider the semidefinite program over a symmetric 2x2 matrix X:\nMinimize <C, X> subject to <A_i, X> = b_i for i=1..1, and X is positive semidefinite (X \u2ab0 0).\n\nC = [[-2, 0], [0, -2]]\nA_1 = [[3, -2.5], [-2.5, -3]]\nb_1 = -32.0\n\nWhat is the minimum value of <C, X> (rounded to 3 decimals)?",
    "answer": "-24.000000322803935"
  },
  {
    "question": "Consider the semidefinite program over a symmetric 2x2 matrix X:\nMinimize <C, X> subject to <A_i, X> = b_i for i=1..1, and X is positive semidefinite (X \u2ab0 0).\n\nC = [[-3, -1], [-1, 1]]\nA_1 = [[-2, 0], [0, -2]]\nb_1 = -24.0\n\nWhat is the minimum value of <C, X> (rounded to 3 decimals)?",
    "answer": "-38.83312403723389"
  }
]